hash_calc/Controller.py
hash_calc/HashCalc.py
hash_calc/__init__.py
hash_calc/__main__.py
hash_calc-1.1.0.dist-info/LICENSE.md
hash_calc-1.1.0.dist-info/METADATA
hash_calc-1.1.0.dist-info/WHEEL
hash_calc-1.1.0.dist-info/entry_points.txt
hash_calc-1.1.0.dist-info/top_level.txt
hash_calc-1.1.0.dist-info/RECORD
