Metadata-Version: 2.1
Name: hash-calc
Version: 1.1.0
Summary: Calculates MD5 and SHA256 hashes for a given file or bytes
Home-page: https://github.com/5f0ne/hash-calc
Author: 5f0
License: MIT
Classifier: Operating System :: OS Independent 
Classifier: Programming Language :: Python :: 3 
Classifier: License :: OSI Approved :: MIT License 
License-File: LICENSE.md
